src/qualitative_reasoning/__init__.py
src/qualitative_reasoning/qr_core.py
src/qualitative_reasoning/qualitative_reasoning_modules/__init__.py
src/qualitative_reasoning/qualitative_reasoning_modules/analysis_behavior.py
src/qualitative_reasoning/qualitative_reasoning_modules/analysis_engine.py
src/qualitative_reasoning/qualitative_reasoning_modules/analysis_engine_refactored.py
src/qualitative_reasoning/qualitative_reasoning_modules/analysis_patterns.py
src/qualitative_reasoning/qualitative_reasoning_modules/analysis_relationships.py
src/qualitative_reasoning/qualitative_reasoning_modules/constraint_engine.py
src/qualitative_reasoning/qualitative_reasoning_modules/core_types.py
src/qualitative_reasoning/qualitative_reasoning_modules/process_activation.py
src/qualitative_reasoning/qualitative_reasoning_modules/process_causal_reasoning.py
src/qualitative_reasoning/qualitative_reasoning_modules/process_conditions.py
src/qualitative_reasoning/qualitative_reasoning_modules/process_engine.py
src/qualitative_reasoning/qualitative_reasoning_modules/process_engine_refactored.py
src/qualitative_reasoning/qualitative_reasoning_modules/process_management.py
src/qualitative_reasoning/qualitative_reasoning_modules/simulation_engine.py
src/qualitative_reasoning/qualitative_reasoning_modules/visualization_core.py
src/qualitative_reasoning/qualitative_reasoning_modules/visualization_engine.py
src/qualitative_reasoning/qualitative_reasoning_modules/visualization_engine_refactored.py
src/qualitative_reasoning/qualitative_reasoning_modules/visualization_exports.py
src/qualitative_reasoning/qualitative_reasoning_modules/visualization_history.py
src/qualitative_reasoning/qualitative_reasoning_modules/visualization_reports.py
qualitative_reasoning-1.4.0.dist-info/METADATA
qualitative_reasoning-1.4.0.dist-info/WHEEL
qualitative_reasoning-1.4.0.dist-info/licenses/LICENSE
qualitative_reasoning-1.4.0.dist-info/RECORD
